pyspark_dq/__init__.py
pyspark_dq/config.py
pyspark_dq/dq_checks.py
pyspark_dq/run_dq.py
pyspark_dq/validate_checks.py
pyspark_dq_framework-1.0.1.dist-info/licenses/LICENSE.txt
pyspark_dq_framework-1.0.1.dist-info/METADATA
pyspark_dq_framework-1.0.1.dist-info/WHEEL
pyspark_dq_framework-1.0.1.dist-info/top_level.txt
pyspark_dq_framework-1.0.1.dist-info/RECORD
