Metadata-Version: 2.4
Name: pyspark-dq-framework
Version: 1.0.1
Summary: A PySpark-based Data Quality Framework using YAML-configurable checks.
Home-page: https://github.com/nitin-chaudhari/pyspark-dq-framework
Author: Nitin Chaudhari
Author-email: nitinchaudhariofficial@gmail.com
Classifier: Programming Language :: Python :: 3
Classifier: License :: OSI Approved :: MIT License
Classifier: Operating System :: OS Independent
Classifier: Topic :: Software Development :: Libraries
Classifier: Topic :: Utilities
Requires-Python: >=3.7
License-File: LICENSE.txt
Requires-Dist: pyyaml
Provides-Extra: pyspark
Requires-Dist: pyspark>=3.5.5; extra == "pyspark"
Dynamic: author
Dynamic: author-email
Dynamic: classifier
Dynamic: description
Dynamic: description-content-type
Dynamic: home-page
Dynamic: license-file
Dynamic: provides-extra
Dynamic: requires-dist
Dynamic: requires-python
Dynamic: summary
